Lgk/__init__.py
Lgk2-1.2.2.7.dist-info/LICENSE.py
Lgk2-1.2.2.7.dist-info/METADATA
Lgk2-1.2.2.7.dist-info/WHEEL
Lgk2-1.2.2.7.dist-info/top_level.txt
Lgk2-1.2.2.7.dist-info/RECORD
